<?xml version="1.0"?>
<Room Num="1634" Version="2.41b" Area="ocean">
  <Name>Leviathan Drive/Hillcrest Drive Intersection</Name>
  <ShortDescription>You are at the intersection of Hillcrest Drive and Leviathan Drive.</ShortDescription>
  <LongDescription>Hillcrest Drive, running east to west, intersects Leviathan Drive, running
north and south.  Hillcrest Drive is one of the longer roads in town,
running from the east city walls to the west city walls without being
detoured or interrupted.  Similarly, Leviathan Drive spans the city from
north to south city walls.</LongDescription>
  
  
  
  <Established>727141642</Established>
  <Flags/>
  <Wander>
    <RandomMonsters/>
  </Wander>
  <Track>
    <Direction>south</Direction>
    <Size>5</Size>
    <Num>1</Num>
  </Track>
  <PermMobs/>
  <PermObjs/>
  <LastTimes/>
  <Objects/>
  <Creatures/>
  <Exits>
    <Exit Name="north">
      <Keys/>
      <Room Area="ocean">1640</Room>
      <Flags/>
    </Exit>
    <Exit Name="south">
      <Keys/>
      <Room Area="ocean">1641</Room>
      <Flags/>
    </Exit>
    <Exit Name="west">
      <Keys/>
      <Room Area="ocean">1633</Room>
      <Flags/>
    </Exit>
    <Exit Name="east">
      <Keys/>
      <Room Area="ocean">1797</Room>
      <Flags/>
    </Exit>
  </Exits>
</Room>
