<?xml version="1.0"?>
<Room Num="2476" Version="2.40" Area="ocean">
  <Name>Ranger Training Location</Name>
  <ShortDescription>You are in the training location for level eleven rangers.</ShortDescription>
  <LongDescription>Since you have progressed this far, you are worthy to train at this 
location to advance to the next level.  You will need to track further
into the forest to train at level twelve.</LongDescription>
  <LowLevel>11</LowLevel>
  <HighLevel>11</HighLevel>
  
  <Established>727255580</Established>
  <Flags>
    <Bit Num="4"/>
    <Bit Num="5"/>
    <Bit Num="6"/>
    <Bit Num="12"/>
    <Bit Num="14"/>
  </Flags>
  <Wander>
    <RandomMonsters/>
  </Wander>
  <Track>
    <Direction>out</Direction>
  </Track>
  <PermMobs/>
  <PermObjs/>
  <LastTimes/>
  <Objects/>
  <Creatures/>
  <Exits>
    <Exit Name="out">
      <Keys/>
      <Room Area="ocean">2475</Room>
      <Flags/>
    </Exit>
  </Exits>
</Room>
